README
setup.py
nudge/__init__.py
nudge/arg.py
nudge/error.py
nudge/json.py
nudge/log.py
nudge/project.py
nudge/publisher.py
nudge/renderer.py
nudge/utils.py
nudge/validator.py
nudge.egg-info/PKG-INFO
nudge.egg-info/SOURCES.txt
nudge.egg-info/dependency_links.txt
nudge.egg-info/namespace_packages.txt
nudge.egg-info/not-zip-safe
nudge.egg-info/requires.txt
nudge.egg-info/top_level.txt