Metadata-Version: 1.0
Name: nudge
Version: 0.6.5
Summary: Nudge
Home-page: evite.github.com/nudge/
Author: Evite Inc
Author-email: unix@evite.com
License: UNKNOWN
Platform: UNKNOWN
Classifier: Development Status :: 4 - Beta
Classifier: Environment :: Web Environment
Classifier: Intended Audience :: Developers
Classifier: Operating System :: MacOS :: MacOS X
Classifier: Operating System :: Microsoft :: Windows
Classifier: Operating System :: POSIX
Classifier: Programming Language :: Python
Classifier: Topic :: Software Development :: Bug Tracking
